README.md
setup.py
chinacoordtran/COOR_XY.py
chinacoordtran/CoordTran.py
chinacoordtran/__init__.py
chinacoordtran/bd09togcj02.py
chinacoordtran/gcj02tobd09.py
chinacoordtran/gcj02towgs84.py
chinacoordtran/utils.py
chinacoordtran/wgs84togcj02.py
chinacoordtran.egg-info/PKG-INFO
chinacoordtran.egg-info/SOURCES.txt
chinacoordtran.egg-info/dependency_links.txt
chinacoordtran.egg-info/top_level.txt