Metadata-Version: 2.1
Name: chinacoordtran
Version: 1.1
Summary: Coordinate Transformation for china 
Home-page: https://github.com/thiswildidea/chinacoordtran_py
Author: thiswildidea
Author-email: 314984468@qq.com
License: UNKNOWN
Platform: UNKNOWN
Classifier: Programming Language :: Python :: 3
Classifier: License :: OSI Approved :: MIT License
Classifier: Operating System :: OS Independent
